{
  "optimal_N": 1,
  "optimal_threshold": 0.4,
  "best_score": 0.9416666666666667,
  "raw_results": [
    {
      "N": 1,
      "threshold": 0.4,
      "accuracy": 0.9416666666666667,
      "fpr": 0.0,
      "score": 0.9416666666666667
    },
    {
      "N": 1,
      "threshold": 0.5,
      "accuracy": 0.925,
      "fpr": 0.0,
      "score": 0.925
    },
    {
      "N": 1,
      "threshold": 0.6,
      "accuracy": 0.9083333333333333,
      "fpr": 0.0,
      "score": 0.9083333333333333
    },
    {
      "N": 1,
      "threshold": 0.7,
      "accuracy": 0.8833333333333333,
      "fpr": 0.0,
      "score": 0.8833333333333333
    },
    {
      "N": 1,
      "threshold": 0.8,
      "accuracy": 0.8083333333333333,
      "fpr": 0.0,
      "score": 0.8083333333333333
    },
    {
      "N": 1,
      "threshold": 0.9,
      "accuracy": 0.625,
      "fpr": 0.0,
      "score": 0.625
    },
    {
      "N": 3,
      "threshold": 0.4,
      "accuracy": 0.8477777777777777,
      "fpr": 0.18666666666666668,
      "score": 0.5677777777777777
    },
    {
      "N": 3,
      "threshold": 0.5,
      "accuracy": 0.8344444444444444,
      "fpr": 0.16666666666666666,
      "score": 0.5844444444444444
    },
    {
      "N": 3,
      "threshold": 0.6,
      "accuracy": 0.8216666666666667,
      "fpr": 0.1111111111111111,
      "score": 0.655
    },
    {
      "N": 3,
      "threshold": 0.7,
      "accuracy": 0.8005555555555556,
      "fpr": 0.0022222222222222222,
      "score": 0.7972222222222223
    },
    {
      "N": 3,
      "threshold": 0.8,
      "accuracy": 0.735,
      "fpr": 0.0,
      "score": 0.735
    },
    {
      "N": 3,
      "threshold": 0.9,
      "accuracy": 0.5761111111111111,
      "fpr": 0.0,
      "score": 0.5761111111111111
    },
    {
      "N": 5,
      "threshold": 0.4,
      "accuracy": 0.7527777777777778,
      "fpr": 0.38666666666666666,
      "score": 0.1727777777777778
    },
    {
      "N": 5,
      "threshold": 0.5,
      "accuracy": 0.7444444444444445,
      "fpr": 0.32222222222222224,
      "score": 0.26111111111111107
    },
    {
      "N": 5,
      "threshold": 0.6,
      "accuracy": 0.7316666666666667,
      "fpr": 0.18666666666666668,
      "score": 0.45166666666666666
    },
    {
      "N": 5,
      "threshold": 0.7,
      "accuracy": 0.7155555555555555,
      "fpr": 0.13333333333333333,
      "score": 0.5155555555555555
    },
    {
      "N": 5,
      "threshold": 0.8,
      "accuracy": 0.6616666666666666,
      "fpr": 0.008888888888888889,
      "score": 0.6483333333333333
    },
    {
      "N": 5,
      "threshold": 0.9,
      "accuracy": 0.5272222222222223,
      "fpr": 0.0,
      "score": 0.5272222222222223
    },
    {
      "N": 7,
      "threshold": 0.4,
      "accuracy": 0.6594444444444445,
      "fpr": 0.5666666666666667,
      "score": -0.19055555555555548
    },
    {
      "N": 7,
      "threshold": 0.5,
      "accuracy": 0.6538888888888889,
      "fpr": 0.4955555555555556,
      "score": -0.08944444444444455
    },
    {
      "N": 7,
      "threshold": 0.6,
      "accuracy": 0.6466666666666666,
      "fpr": 0.31333333333333335,
      "score": 0.17666666666666658
    },
    {
      "N": 7,
      "threshold": 0.7,
      "accuracy": 0.6322222222222222,
      "fpr": 0.18,
      "score": 0.3622222222222222
    },
    {
      "N": 7,
      "threshold": 0.8,
      "accuracy": 0.5883333333333334,
      "fpr": 0.08666666666666667,
      "score": 0.45833333333333337
    },
    {
      "N": 7,
      "threshold": 0.9,
      "accuracy": 0.47833333333333333,
      "fpr": 0.0,
      "score": 0.47833333333333333
    },
    {
      "N": 10,
      "threshold": 0.4,
      "accuracy": 0.5577777777777778,
      "fpr": 0.8133333333333334,
      "score": -0.6622222222222222
    },
    {
      "N": 10,
      "threshold": 0.5,
      "accuracy": 0.5338888888888889,
      "fpr": 0.6955555555555556,
      "score": -0.5094444444444446
    },
    {
      "N": 10,
      "threshold": 0.6,
      "accuracy": 0.5144444444444445,
      "fpr": 0.4955555555555556,
      "score": -0.22888888888888892
    },
    {
      "N": 10,
      "threshold": 0.7,
      "accuracy": 0.5077777777777778,
      "fpr": 0.30444444444444446,
      "score": 0.05111111111111111
    },
    {
      "N": 10,
      "threshold": 0.8,
      "accuracy": 0.4766666666666667,
      "fpr": 0.12666666666666668,
      "score": 0.2866666666666667
    },
    {
      "N": 10,
      "threshold": 0.9,
      "accuracy": 0.4061111111111111,
      "fpr": 0.0022222222222222222,
      "score": 0.40277777777777773
    },
    {
      "N": 15,
      "threshold": 0.4,
      "accuracy": 0.6811111111111111,
      "fpr": 0.9511111111111111,
      "score": -0.7455555555555556
    },
    {
      "N": 15,
      "threshold": 0.5,
      "accuracy": 0.6483333333333333,
      "fpr": 0.8866666666666667,
      "score": -0.6816666666666668
    },
    {
      "N": 15,
      "threshold": 0.6,
      "accuracy": 0.5038888888888889,
      "fpr": 0.7622222222222222,
      "score": -0.6394444444444444
    },
    {
      "N": 15,
      "threshold": 0.7,
      "accuracy": 0.3016666666666667,
      "fpr": 0.5244444444444445,
      "score": -0.48500000000000004
    },
    {
      "N": 15,
      "threshold": 0.8,
      "accuracy": 0.2927777777777778,
      "fpr": 0.24444444444444444,
      "score": -0.07388888888888884
    },
    {
      "N": 15,
      "threshold": 0.9,
      "accuracy": 0.2822222222222222,
      "fpr": 0.06666666666666667,
      "score": 0.1822222222222222
    }
  ]
}